.coveragerc
.gitignore
.travis.yml
LICENSE
MANIFEST.in
README.rst
build-docs.sh
conftest.py
pyproject.toml
pytest.ini
setup.py
bin/evolution
configpp/__init__.py
configpp.egg-info/PKG-INFO
configpp.egg-info/SOURCES.txt
configpp.egg-info/dependency_links.txt
configpp.egg-info/requires.txt
configpp.egg-info/top_level.txt
configpp/evolution/__init__.py
configpp/evolution/chain.py
configpp/evolution/cli.py
configpp/evolution/core.py
configpp/evolution/exceptions.py
configpp/evolution/revision.py
configpp/evolution/utils.py
configpp/evolution/templates/script.py.tmpl
configpp/soil/__init__.py
configpp/soil/config.py
configpp/soil/exception.py
configpp/soil/group.py
configpp/soil/transform.py
configpp/soil/transport.py
configpp/soil/utils.py
configpp/tree/__init__.py
configpp/tree/custom_item_factories.py
configpp/tree/custom_items.py
configpp/tree/exceptions.py
configpp/tree/item_factory.py
configpp/tree/items.py
configpp/tree/settings.py
configpp/tree/tree.py
docs/Makefile
docs/requirements.txt
docs/source/conf.py
docs/source/configpp.evolution.rst
docs/source/configpp.rst
docs/source/configpp.soil.rst
docs/source/configpp.tree.rst
docs/source/index.rst
docs/source/modules.rst
docs/source/.doctrees/configpp.doctree
docs/source/.doctrees/configpp.evolution.doctree
docs/source/.doctrees/configpp.soil.doctree
docs/source/.doctrees/configpp.tree.doctree
docs/source/.doctrees/environment.pickle
docs/source/.doctrees/index.doctree
docs/source/.doctrees/modules.doctree
docs/source/.doctrees/test_evolution.doctree
docs/source/.doctrees/test_soil.doctree
docs/source/.doctrees/test_tree.doctree
docs/source/.doctrees/examples/evolution.doctree
docs/source/.doctrees/examples/soil.doctree
docs/source/.doctrees/examples/tree.doctree
docs/source/examples/evolution.rst
docs/source/examples/soil.rst
docs/source/examples/tree.rst
examples/soil/load_simple.py
examples/tree/simple_param_default.py
test/test_evolution/__init__.py
test/test_evolution/test_chain.py
test/test_evolution/test_core.py
test/test_evolution/test_revision.py
test/test_evolution/test_upgrade.py
test/test_evolution/utils.py
test/test_soil/__init__.py
